{
  "last_known_lines": 33535,
  "accumulated_patch": 0,
  "last_version": "0.1.0",
  "history": [
    {
      "timestamp": "2026-06-14T19:51:20.416959",
      "version": "0.1.0",
      "total_lines": 33540,
      "new_lines": 5,
      "patch_increment": 0
    },
    {
      "timestamp": "2026-06-14T19:52:26.901087",
      "version": "0.1.0",
      "total_lines": 33540,
      "new_lines": 5,
      "patch_increment": 0
    },
    {
      "timestamp": "2026-06-14T19:53:52.693603",
      "version": "0.1.0",
      "total_lines": 33540,
      "new_lines": 5,
      "patch_increment": 0
    },
    {
      "timestamp": "2026-06-14T19:55:58.934460",
      "version": "0.1.0",
      "total_lines": 33540,
      "new_lines": 5,
      "patch_increment": 0
    },
    {
      "timestamp": "2026-06-14T19:58:44.834409",
      "version": "0.1.0",
      "total_lines": 33540,
      "new_lines": 5,
      "patch_increment": 0
    },
    {
      "timestamp": "2026-06-14T19:58:57.091801",
      "version": "0.1.0",
      "total_lines": 33540,
      "new_lines": 5,
      "patch_increment": 0
    }
  ]
}